{
  "title": "上演二十四時間",
  "BPM": "87.5",
  "author": "Losstime Life",
  "nando": "★★★★★",
  "end": "110000",
  "notes": [
    { "timing": "4639.507", "lean": "c"},
    { "timing": "5317.9", "lean": "r"},
    { "timing": "5980.566", "lean": "l"},
    { "timing": "6709.5", "lean": "c"},
    { "timing": "7405.301", "lean": "r"},
    { "timing": "8084.533", "lean": "l"},
    { "timing": "8747.656", "lean": "c"},
    { "timing": "9443", "lean": "r"},
    { "timing": "10138.94", "lean": "l"},
    { "timing": "10801.47", "lean": "c"},
    { "timing": "11480.7", "lean": "r"},
    { "timing": "12159.93", "lean": "l"},
    { "timing": "12888.91", "lean": "c"},
    { "timing": "13551.71", "lean": "r"},
    { "timing": "14197.85", "lean": "l"},
    { "timing": "14860.79", "lean": "c"},
    { "timing": "15224.77", "lean": "r"},
    { "timing": "16550.1", "lean": "l"},
    { "timing": "17925.13", "lean": "c"},
    { "timing": "19333.3", "lean": "r"},
    { "timing": "19681.2", "lean": "l"},
    { "timing": "20029.1", "lean": "c"},
    { "timing": "20426.93", "lean": "r"},
    { "timing": "21123.07", "lean": "l"},
    { "timing": "21801.96", "lean": "c"},
    { "timing": "22447.99", "lean": "r"},
    { "timing": "23127.07", "lean": "l"},
    { "timing": "23789.73", "lean": "c"},
    { "timing": "24535.96", "lean": "r"},
    { "timing": "25247.6", "lean": "l"},
    { "timing": "25578.93", "lean": "c"},
    { "timing": "25943.4", "lean": "r"},
    { "timing": "26655.82", "lean": "l"},
    { "timing": "27301.87", "lean": "c"},
    { "timing": "27997.67", "lean": "r"},
    { "timing": "28677.1", "lean": "l"},
    { "timing": "29389.27", "lean": "c"},
    { "timing": "30035.89", "lean": "r"},
    { "timing": "30731.17", "lean": "l"},
    { "timing": "31062.5", "lean": "c"},
    { "timing": "31410.96", "lean": "r"},
    { "timing": "32073.22", "lean": "l"},
    { "timing": "32802.04", "lean": "c"},
    { "timing": "33448.1", "lean": "r"},
    { "timing": "34160.47", "lean": "l"},
    { "timing": "34856.27", "lean": "c"},
    { "timing": "35535.92", "lean": "r"},
    { "timing": "36198.42", "lean": "l"},
    { "timing": "36911.07", "lean": "c"},
    { "timing": "37589.81", "lean": "r"},
    { "timing": "38252.69", "lean": "l"},
    { "timing": "38898.53", "lean": "c"},
    { "timing": "39627.47", "lean": "r"},
    { "timing": "40356.46", "lean": "l"},
    { "timing": "41002.6", "lean": "c"},
    { "timing": "41682.09", "lean": "r"},
    { "timing": "42361.09", "lean": "l"},
    { "timing": "43089.9", "lean": "c"},
    { "timing": "43752.57", "lean": "r"},
    { "timing": "44431.8", "lean": "l"},
    { "timing": "45111.06", "lean": "c"},
    { "timing": "45790.71", "lean": "r"},
    { "timing": "46486.75", "lean": "l"},
    { "timing": "47165.42", "lean": "c"},
    { "timing": "47513.2", "lean": "r"},
    { "timing": "47844.54", "lean": "l"},
    { "timing": "48523.83", "lean": "c"},
    { "timing": "49220.2", "lean": "r"},
    { "timing": "49882.23", "lean": "l"},
    { "timing": "50544.9", "lean": "c"},
    { "timing": "51257.27", "lean": "r"},
    { "timing": "51986.2", "lean": "l"},
    { "timing": "52648.87", "lean": "c"},
    { "timing": "52980.2", "lean": "r"},
    { "timing": "53311.72", "lean": "l"},
    { "timing": "53676.07", "lean": "c"},
    { "timing": "54173.29", "lean": "r"},
    { "timing": "54703.13", "lean": "l"},
    { "timing": "55249.84", "lean": "c"},
    { "timing": "55730.27", "lean": "r"},
    { "timing": "56426.07", "lean": "l"},
    { "timing": "56972.85", "lean": "c"},
    { "timing": "57486.34", "lean": "r"},
    { "timing": "57966.96", "lean": "l"},
    { "timing": "58464.13", "lean": "c"},
    { "timing": "59143", "lean": "r"},
    { "timing": "59707.21", "lean": "l"},
    { "timing": "60204.07", "lean": "c"},
    { "timing": "60716.83", "lean": "r"},
    { "timing": "61230.4", "lean": "l"},
    { "timing": "61926.4", "lean": "c"},
    { "timing": "62257.54", "lean": "r"},
    { "timing": "62622.11", "lean": "l"},
    { "timing": "62953.36", "lean": "c"},
    { "timing": "63284.78", "lean": "r"},
    { "timing": "63649.13", "lean": "l"},
    { "timing": "63997.29", "lean": "c"},
    { "timing": "64378.13", "lean": "r"},
    { "timing": "65024.17", "lean": "l"},
    { "timing": "65703.59", "lean": "c"},
    { "timing": "66382.63", "lean": "r"},
    { "timing": "67078.44", "lean": "l"},
    { "timing": "67741.1", "lean": "c"},
    { "timing": "68436.9", "lean": "r"},
    { "timing": "69099.98", "lean": "l"},
    { "timing": "69447.95", "lean": "c"},
    { "timing": "69811.94", "lean": "r"},
    { "timing": "70507.91", "lean": "l"},
    { "timing": "71186.98", "lean": "c"},
    { "timing": "71866.2", "lean": "r"},
    { "timing": "72545.43", "lean": "l"},
    { "timing": "73208.1", "lean": "c"},
    { "timing": "73903.9", "lean": "r"},
    { "timing": "74600.02", "lean": "l"},
    { "timing": "74947.6", "lean": "c"},
    { "timing": "75295.87", "lean": "r"},
    { "timing": "75974.78", "lean": "l"},
    { "timing": "76654.32", "lean": "c"},
    { "timing": "77300.33", "lean": "r"},
    { "timing": "78012.44", "lean": "l"},
    { "timing": "78708.23", "lean": "c"},
    { "timing": "79387.47", "lean": "r"},
    { "timing": "80083.88", "lean": "l"},
    { "timing": "80447.74", "lean": "c"},
    { "timing": "80795.63", "lean": "r"},
    { "timing": "81508", "lean": "l"},
    { "timing": "82171.09", "lean": "c"},
    { "timing": "82817.39", "lean": "r"},
    { "timing": "83529.39", "lean": "l"},
    { "timing": "84208.45", "lean": "c"},
    { "timing": "84937.63", "lean": "r"},
    { "timing": "85583.84", "lean": "l"},
    { "timing": "85914.73", "lean": "c"},
    { "timing": "86279.59", "lean": "r"},
    { "timing": "86627.56", "lean": "l"},
    { "timing": "87090.96", "lean": "c"},
    { "timing": "87621.18", "lean": "r"},
    { "timing": "87952.43", "lean": "l"},
    { "timing": "88466.27", "lean": "c"},
    { "timing": "88996.13", "lean": "r"},
    { "timing": "89327.47", "lean": "l"},
    { "timing": "89841.31", "lean": "c"},
    { "timing": "90387.73", "lean": "r"},
    { "timing": "91066.97", "lean": "l"},
    { "timing": "91713.06", "lean": "c"},
    { "timing": "92027.83", "lean": "r"},
    { "timing": "92557.97", "lean": "l"},
    { "timing": "93071.83", "lean": "c"},
    { "timing": "93403.38", "lean": "r"},
    { "timing": "93949.7", "lean": "l"},
    { "timing": "94446.57", "lean": "c"},
    { "timing": "94795.2", "lean": "r"},
    { "timing": "95325.3", "lean": "l"},
    { "timing": "95887.87", "lean": "c"},
    { "timing": "96533.96", "lean": "r"},
    { "timing": "97196.92", "lean": "l"},
    { "timing": "97561.1", "lean": "c"},
    { "timing": "98058.31", "lean": "r"},
    { "timing": "98555.1", "lean": "l"},
    { "timing": "98903.05", "lean": "c"},
    { "timing": "99449.7", "lean": "r"},
    { "timing": "99930.48", "lean": "l"},
    { "timing": "100261.8", "lean": "c"},
    { "timing": "100808.6", "lean": "r"},
    { "timing": "101338.9", "lean": "l"},
    { "timing": "102017.5", "lean": "c"},
    { "timing": "102696.8", "lean": "r"},
    { "timing": "103044.7", "lean": "l"},
    { "timing": "103541.7", "lean": "c"},
    { "timing": "104071.8", "lean": "r"},
    { "timing": "104403.4", "lean": "l"},
    { "timing": "104949.8", "lean": "c"},
    { "timing": "105447", "lean": "r"}
  ]
}